croco_cli/.DS_Store
croco_cli/__init__.py
croco_cli/__main__.py
croco_cli/_database.py
croco_cli/cli/__init__.py
croco_cli/cli/_change.py
croco_cli/cli/_cli.py
croco_cli/cli/_export.py
croco_cli/cli/_import.py
croco_cli/cli/_init.py
croco_cli/cli/_install.py
croco_cli/cli/_make.py
croco_cli/cli/_reset.py
croco_cli/cli/_set.py
croco_cli/cli/_user.py
croco_cli/croco_echo.py
croco_cli/exceptions.py
croco_cli/globals.py
croco_cli/tools/__init__.py
croco_cli/tools/echo.py
croco_cli/tools/keymode.py
croco_cli/tools/option.py
croco_cli/tools/types.py
croco_cli/types.py
croco_cli/utils.py
croco_cli-0.3.1.post2.dist-info/LICENSE
croco_cli-0.3.1.post2.dist-info/METADATA
croco_cli-0.3.1.post2.dist-info/WHEEL
croco_cli-0.3.1.post2.dist-info/entry_points.txt
croco_cli-0.3.1.post2.dist-info/RECORD
