Metadata-Version: 2.1
Name: croco_cli
Version: 0.3.1.post2
Summary: The CLI for developing Web3-based projects in Croco Factory
Home-page: https://github.com/CrocoFactory/croco-cli
License: MIT
Author: Alexey
Author-email: axbelenkov@gmail.com
Requires-Python: >=3.11,<4.0
Classifier: Development Status :: 4 - Beta
Classifier: Intended Audience :: Developers
Classifier: License :: OSI Approved :: MIT License
Classifier: Operating System :: MacOS
Classifier: Operating System :: Microsoft :: Windows
Classifier: Programming Language :: Python :: 3
Classifier: Programming Language :: Python :: 3.11
Classifier: Programming Language :: Python :: 3.12
Classifier: Programming Language :: Python :: 3 :: Only
Classifier: Topic :: Software Development :: Build Tools
Classifier: Topic :: Software Development :: Version Control :: Git
Requires-Dist: blessed (>=1.20.0,<2.0.0)
Requires-Dist: click (>=8.1.7,<9.0.0)
Requires-Dist: eth-account (>=0.11.0,<0.12.0)
Requires-Dist: peewee (>=3.17.0,<4.0.0)
Requires-Dist: pygithub (>=2.2.0,<3.0.0)
Project-URL: Repository, https://github.com/CrocoFactory/croco-cli
